confcogs/__init__.py
confcogs/core.py
confcogs-0.1.0.dist-info/METADATA
confcogs-0.1.0.dist-info/WHEEL
confcogs-0.1.0.dist-info/top_level.txt
confcogs-0.1.0.dist-info/RECORD
