Metadata-Version: 2.1
Name: confcogs
Version: 0.1.0
Summary: Lib for managing .cogs file
Author: pathset
Author-email: abyzmsamphetamine@gmail.com
License: MIT
Classifier: Programming Language :: Python :: 3
Classifier: License :: OSI Approved :: MIT License
Classifier: Operating System :: OS Independent
Requires-Python: >=3.6
